[
    {
        "id": 0,
        "url": "https://en.wikipedia.org/wiki/Famagusta",
        "city": "Famagusta",
        "country": "Cyprus",
        "country-district": "Gazimağusa District",
        "country-country-(de-facto)": "Northern Cyprus",
        "government-mayor": "İsmail Arter   Simos Ioannou (in exile)",
        "population-municipality": "55,648(District:91,307)",
        "time-zone": "UTC+2 (EET)",
        "time-zone-summer-(dst)": "UTC+3 (EEST)",
        "website": "Famagusta Turkish municipality (in Famagusta)Greek Cypriot municipality (in exile)",
        "lat": "35°07′30″N",
        "long": "33°56′30″E"
    },
    {
        "id": 1,
        "url": "https://en.wikipedia.org/wiki/Kyrenia",
        "city": "Kyrenia",
        "country": "Cyprus",
        "country-district": "Girne District",
        "country-country-(de-facto)": "Northern Cyprus",
        "government-mayor": "Nidai Güngördü (in Kyrenia) Rita Elissaiou Komodiki (in exile)",
        "elevation": "0 m (0 ft)",
        "population-municipality": "45,881 (District:96,663)",
        "time-zone": "UTC+2 (EET)",
        "time-zone-summer-(dst)": "UTC+3 (EEST)",
        "website": "Kyrenia Turkish municipality\\nThe municipality in NC eGov portalGreek Cypriot municipality(in exile)",
        "lat": "35°20′25″N",
        "long": "33°19′09″E"
    },
    {
        "id": 2,
        "url": "https://en.wikipedia.org/wiki/Limassol",
        "city": "Limassol",
        "country": "Cyprus",
        "district": "Limassol District",
        "government-mayor": "Nicos Nicolaides (EDEK)",
        "area-city": "56.87 km (21.96 sq mi)",
        "population-city": "101,000",
        "population-urban": "183,658",
        "population-metro": "240,842",
        "time-zone": "UTC+2 (EET)",
        "time-zone-summer-(dst)": "UTC+3 (EEST)",
        "postal-code": "3010–3150",
        "website": "www.limassolmunicipal.com.cy",
        "lat": "34°40′29″N",
        "long": "33°02′39″E"
    },
    {
        "id": 3,
        "url": "https://en.wikipedia.org/wiki/Larnaca",
        "city": "Larnaca",
        "country": "Cyprus",
        "district": "Larnaca District",
        "government-type": "Municipal council",
        "government-mayor": "Andreas Vyras (AKEL)",
        "elevation": "26 m (85 ft)",
        "population-city": "51,468",
        "population-urban": "84,900",
        "population-metro": "144,200",
        "population-": "The urban population is the aggregate of the populations of Larnaca, Aradippou, Livadia, Dromolaxia, and Meneou",
        "time-zone": "UTC+2 (EET)",
        "time-zone-summer-(dst)": "UTC+3 (EEST)",
        "area-code": "+357 24",
        "website": "www.larnaka.org.cy",
        "lat": "34°55′N",
        "long": "33°38′E"
    },
    {
        "id": 4,
        "url": "https://en.wikipedia.org/wiki/Nicosia",
        "city": "Nicosia",
        "claimed-by": "Republic of Cyprus (internationally recognised)\\n Northern Cyprus (the northern part, recognised only by Turkey)",
        "administered-by": "",
        "southnorth": "Republic of Cyprus\\nNorthern Cyprus (Recognised only by Turkey)",
        "cypriot-district": "Nicosia",
        "government-mayor-of-nicosia-municipality": "Constantinos Yiorkadjis (Ind.)",
        "government-mayor-of-nicosia-turkish-municipality": "Mehmet Harmancı (TDP)",
        "area-land": "51.06 km (19.71 sq mi)",
        "elevation": "220 m (720 ft)",
        "population-capital-city": "South: 55,014\\nNorth: 61,378",
        "population-urban": "South: 244,200\\nNorth: 82,539",
        "population-": "The souths urban includes the municipalities of Nicosia (south), Agios Dometios, Egkomi, Strovolos, Aglantzia, Lakatameia, Anthoupolis, Latsia and Yeri. The norths includes North Nicosia, Gönyeli, Gerolakkos and Kanli.",
        "demonym": "Nicosian",
        "time-zone": "UTC+2 (EET)",
        "time-zone-summer-(dst)": "UTC+3 (EEST)",
        "post-code": "1010–1107",
        "area-code": "+357 22",
        "iso-3166-code": "CY-01",
        "website": "(Republic of Cyprus website-south)www.nicosia.org.cy(Northern Cypriot website-north) www.lefkosabelediyesi.org",
        "lat": "35°10′21″N",
        "long": "33°21′54″E"
    },
    {
        "id": 5,
        "url": "https://en.wikipedia.org/wiki/Paphos",
        "city": "Paphos",
        "country": "Cyprus",
        "district": "Paphos District",
        "government-mayor": "Phedonas Phedonos (DISY)",
        "elevation": "75 m (236 ft)",
        "population-city": "35,961",
        "population-urban": "63,600",
        "population-metro": "90,200",
        "demonym(s)": "Pafitis, Baflı",
        "time-zone": "UTC+2 (EET)",
        "time-zone-summer-(dst)": "UTC+3 (EST)",
        "post-code": "8000–8999",
        "website": "pafos.org.cy",
        "criteria": "Cultural: iii, vi",
        "reference": "79",
        "inscription": "1980 (4th Session)",
        "area": "162.0171 ha",
        "lat": "34°46′N",
        "long": "32°25′E"
    },
    {
        "id": 6,
        "url": "https://en.wikipedia.org/wiki/Achna",
        "city": "Achna",
        "country": "Cyprus",
        "country-district": "Famagusta District",
        "time-zone": "UTC+2 (EET)",
        "time-zone-summer-(dst)": "UTC+3 (EEST)",
        "lat": "35°3′19″N",
        "long": "33°47′4″E"
    },
    {
        "id": 7,
        "url": "https://en.wikipedia.org/wiki/Agia_Marina,_Nicosia",
        "city": "Agia Marina",
        "country": "Cyprus",
        "district": "Nicosia District",
        "population-total": "628",
        "time-zone": "UTC+2 (EET)",
        "time-zone-summer-(dst)": "UTC+3 (EEST)",
        "lat": "35°03′00″N",
        "long": "33°03′0″E"
    },
    {
        "id": 8,
        "url": "https://en.wikipedia.org/wiki/Agia_Marinouda",
        "city": "Agia Marinouda",
        "country": "Cyprus",
        "district": "Paphos District",
        "population-total": "220",
        "time-zone": "UTC+2 (EET)",
        "time-zone-summer-(dst)": "UTC+3 (EEST)",
        "postal-code": "6012",
        "lat": "34°45′39″N",
        "long": "32°28′25″E"
    },
    {
        "id": 9,
        "url": "https://en.wikipedia.org/wiki/Agia_Trias,_Cyprus",
        "city": "Agia Trias",
        "country": "Cyprus",
        "country-district": "İskele District",
        "country-country-(de-facto)": "Northern Cyprus",
        "population-total": "614",
        "climate": "Csa",
        "lat": "35°32′22″N",
        "long": "34°13′10″E"
    },
    {
        "id": 10,
        "url": "https://en.wikipedia.org/wiki/Agia_Varvara,_Paphos",
        "city": "Agia Varvara",
        "country": "Cyprus",
        "district": "Paphos District",
        "population-total": "172",
        "time-zone": "UTC+2 (EET)",
        "time-zone-summer-(dst)": "UTC+3 (EEST)",
        "lat": "34°45′2″N",
        "long": "32°30′41″E"
    },
    {
        "id": 11,
        "url": "https://en.wikipedia.org/wiki/Agioi_Trimithias",
        "city": "Agioi Trimithias",
        "country": "Cyprus",
        "district": "Nicosia District",
        "population-total": "1,529",
        "time-zone": "UTC+2 (EET)",
        "time-zone-summer-(dst)": "UTC+3 (EEST)",
        "lat": "35°6′53″N",
        "long": "33°12′36″E"
    },
    {
        "id": 12,
        "url": "https://en.wikipedia.org/wiki/Agios_Sozomenos",
        "city": "Agios Sozomenos",
        "country": "Cyprus",
        "district": "Nicosia District",
        "population-total": "4",
        "time-zone": "UTC+2 (EET)",
        "time-zone-summer-(dst)": "UTC+3 (EEST)",
        "lat": "35°3′57″N",
        "long": "33°26′18″E"
    },
    {
        "id": 13,
        "url": "https://en.wikipedia.org/wiki/Aglandjia",
        "city": "Aglandjia",
        "country": "Cyprus",
        "district": "Nicosia District",
        "government-type": "Municipality",
        "population-total": "20,783",
        "time-zone": "UTC+2 (EET)",
        "time-zone-summer-(dst)": "UTC+3 (EEST)",
        "postal-code": "4700",
        "website": "http://www.aglantzia.org.cy",
        "lat": "35°08′45″N",
        "long": "33°23′25″E"
    },
    {
        "id": 14,
        "url": "https://en.wikipedia.org/wiki/Agros,_Cyprus",
        "city": "Agros",
        "country": "Cyprus",
        "district": "Limassol District",
        "government-agros-mayor": "Michalis Constantinides",
        "government-agros-community-council": "Members\\nAntonis TsolakisSofoklis AgathokleousPetros KyriakouAndreas LatziasNiki KafkaliaCharis Papachristoforou",
        "elevation": "3,600 ft (1,100 m)",
        "population-total": "804",
        "population-demonym": "Agrotes",
        "time-zone": "UTC+2 (EET)",
        "time-zone-summer-(dst)": "UTC+3 (EEST)",
        "postcode": "4860",
        "website": "www.agros.org.cy",
        "lat": "34°55′N",
        "long": "33°1′E"
    },
    {
        "id": 15,
        "url": "https://en.wikipedia.org/wiki/Akaki,_Cyprus",
        "city": "Akaki",
        "country": "Cyprus",
        "district": "Nicosia District",
        "population-total": "2,675",
        "time-zone": "UTC+2 (EET)",
        "time-zone-summer-(dst)": "UTC+3 (EEST)",
        "lat": "35°8′0″N",
        "long": "33°7′45″E"
    },
    {
        "id": 16,
        "url": "https://en.wikipedia.org/wiki/Akanthou",
        "city": "Akanthou",
        "country": "Cyprus",
        "country-district": "Gazimağusa District",
        "country-country-(de-facto)": "Northern Cyprus",
        "government-mayor": "A. Hayri Orçan",
        "population-total": "1,459",
        "website": "Tatlısu Turkish Municipality\\nThe municipality in NC eGov portal",
        "lat": "35°22′27″N",
        "long": "33°45′21″E"
    },
    {
        "id": 17,
        "url": "https://en.wikipedia.org/wiki/Akrotiri_and_Dhekelia",
        "city": "Akrotiri",
        "lat": "34°35′N",
        "long": "32°59′E"
    },
    {
        "id": 18,
        "url": "https://en.wikipedia.org/wiki/Amargeti",
        "city": "Amargeti",
        "country": "Cyprus",
        "district": "Paphos District",
        "elevation": "391 m (1,283 ft)",
        "population-total": "171",
        "time-zone": "UTC+2 (EET)",
        "time-zone-summer-(dst)": "UTC+3 (EEST)",
        "postal-code": "6220",
        "lat": "34°49′25″N",
        "long": "32°34′57″E"
    },
    {
        "id": 19,
        "url": "https://en.wikipedia.org/wiki/Amathous",
        "city": "Amathous",
        "lat": "34°42′45″N",
        "long": "33°08′30″E"
    },
    {
        "id": 20,
        "url": "https://en.wikipedia.org/wiki/Anarita",
        "city": "Anarita",
        "country": "Cyprus",
        "district": "Paphos District",
        "population-total": "368 (2,001)",
        "time-zone": "UTC+2 (EET)",
        "time-zone-summer-(dst)": "UTC+3 (EEST)",
        "postal-code": "6107",
        "website": "http://www.anarita.org/",
        "lat": "34°44′23″N",
        "long": "32°32′4″E"
    },
    {
        "id": 21,
        "url": "https://en.wikipedia.org/wiki/Apostolos_Andreas",
        "city": "Apostolos Andreas",
        "lat": "35°39′33″N",
        "long": "34°34′26″E"
    },
    {
        "id": 22,
        "url": "https://en.wikipedia.org/wiki/Argaki",
        "city": "Argaki",
        "country": "Cyprus",
        "country-district": "Güzelyurt District",
        "country-country-(de-facto)": "Northern Cyprus",
        "population-total": "1,008",
        "time-zone": "UTC+2 (EET)",
        "time-zone-summer-(dst)": "UTC+3 (EEST)",
        "lat": "35°10′47″N",
        "long": "33°02′07″E"
    },
    {
        "id": 23,
        "url": "https://en.wikipedia.org/wiki/Arminou",
        "city": "Arminou",
        "country": "Cyprus",
        "district": "Paphos District",
        "population-total": "26",
        "time-zone": "UTC+2 (EET)",
        "time-zone-summer-(dst)": "UTC+3 (EEST)",
        "postal-code": "8625",
        "lat": "34°51′42″N",
        "long": "32°43′10″E"
    },
    {
        "id": 24,
        "url": "https://en.wikipedia.org/wiki/Athienou",
        "city": "Athienou",
        "country": "Cyprus",
        "district": "Larnaca District",
        "population-total": "5,017",
        "time-zone": "UTC+2 (EET)",
        "time-zone-summer-(dst)": "UTC+3 (EEST)",
        "postal-code": "7600",
        "website": "www.athienou.org.cy",
        "lat": "35°04′N",
        "long": "33°32′E"
    },
    {
        "id": 25,
        "url": "https://en.wikipedia.org/wiki/Asha,_Cyprus",
        "city": "Asha",
        "country": "Cyprus",
        "country-district": "Gazimağusa District",
        "country-country-(de-facto)": "Northern Cyprus",
        "government-mayor": "Habil Tülücü",
        "population-total": "3,561",
        "time-zone": "UTC+2 (EET)",
        "time-zone-summer-(dst)": "UTC+3 (EEST)",
        "website": "Turkish Cypriot municipality",
        "lat": "35°9′33″N",
        "long": "33°36′36″E"
    },
    {
        "id": 26,
        "url": "https://en.wikipedia.org/wiki/Asinou",
        "city": "Asinou",
        "country": "Cyprus",
        "district": "Nicosia District",
        "population-total": "426",
        "time-zone": "UTC+2 (EET)",
        "time-zone-summer-(dst)": "UTC+3 (EEST)",
        "lat": "35°4′0″N",
        "long": "32°59′0″E"
    },
    {
        "id": 27,
        "url": "https://en.wikipedia.org/wiki/Askas",
        "city": "Askas",
        "country": "Cyprus",
        "district": "Nicosia District",
        "population-total": "187",
        "time-zone": "UTC+2 (EET)",
        "time-zone-summer-(dst)": "UTC+3 (EEST)",
        "website": "http://www.askas.org/",
        "lat": "34°56′N",
        "long": "33°05′E"
    },
    {
        "id": 28,
        "url": "https://en.wikipedia.org/wiki/Astromeritis",
        "city": "Astromeritis",
        "country": "Cyprus",
        "district": "Nicosia District",
        "government-type": "Community council",
        "government-president": "Aris Constantinou",
        "elevation": "160 m (520 ft)",
        "population-total": "2,307",
        "time-zone": "UTC+2 (EET)",
        "time-zone-summer-(dst)": "UTC+3 (EEST)",
        "postal-code": "2722",
        "website": "http://www.astromeritis.org/",
        "lat": "35°8′0″N",
        "long": "33°2′0″E"
    },
    {
        "id": 29,
        "url": "https://en.wikipedia.org/wiki/Ayia_Napa",
        "city": "Ayia Napa",
        "country": "Cyprus",
        "district": "Famagusta District",
        "government-mayor": "Christos Zannetou",
        "area-total": "12.150 sq mi (31.469 km)",
        "population-total": "3,200 (year round); 40,000 (active)",
        "time-zone": "UTC+2 (EET)",
        "time-zone-summer-(dst)": "UTC+3 (EEST)",
        "area-code": "5330",
        "website": "http://www.ayianapa.org.cy/",
        "lat": "34°59′N",
        "long": "34°00′E"
    },
    {
        "id": 30,
        "url": "https://en.wikipedia.org/wiki/Ayios_Dhometios",
        "city": "Ayios Dhometios",
        "country": "Cyprus",
        "district": "Nicosia District",
        "government-mayor": "Dr. Kostas Petrou",
        "population-total": "12,456",
        "time-zone": "UTC+2 (EET)",
        "time-zone-summer-(dst)": "UTC+3 (EEST)",
        "website": "http://www.dad.org.cy/",
        "lat": "35°11′0″N",
        "long": "33°20′0″E"
    },
    {
        "id": 31,
        "url": "https://en.wikipedia.org/wiki/Bellapais",
        "city": "Bellapais",
        "country": "Cyprus",
        "country-district": "Girne District",
        "country-country-(de-facto)": "Northern Cyprus",
        "time-zone": "UTC+2 (EET)",
        "time-zone-summer-(dst)": "UTC+3 (EEST)",
        "lat": "35°18′N",
        "long": "33°21′E"
    },
    {
        "id": 32,
        "url": "https://en.wikipedia.org/wiki/Buffavento",
        "city": "Buffavento",
        "lat": "35°17′15″N",
        "long": "33°24′37″E"
    },
    {
        "id": 33,
        "url": "https://en.wikipedia.org/wiki/Chirokitia",
        "city": "Chirokitia",
        "lat": "34°47′48.21″N",
        "long": "33°20′37.39″E"
    },
    {
        "id": 34,
        "url": "https://en.wikipedia.org/wiki/Chloraka",
        "city": "Chloraka",
        "country": "Cyprus",
        "district": "Paphos District",
        "elevation": "89 m (292 ft)",
        "population-total": "4,420",
        "time-zone": "UTC+2 (EET)",
        "time-zone-summer-(dst)": "UTC+3 (EEST)",
        "postal-code": "8220",
        "lat": "34°48′4″N",
        "long": "32°24′31″E"
    },
    {
        "id": 35,
        "url": "https://en.wikipedia.org/wiki/Dali,_Cyprus",
        "city": "Dali",
        "country": "Cyprus",
        "district": "Nicosia District",
        "population-total": "10,466",
        "time-zone": "UTC+2 (EET)",
        "time-zone-summer-(dst)": "UTC+3 (EEST)",
        "website": "dali.org.cy",
        "lat": "35°1′16″N",
        "long": "33°25′12″E"
    },
    {
        "id": 36,
        "url": "https://en.wikipedia.org/wiki/Achna",
        "city": "Dasaki tis Achnas",
        "country": "Cyprus",
        "country-district": "Famagusta District",
        "time-zone": "UTC+2 (EET)",
        "time-zone-summer-(dst)": "UTC+3 (EEST)",
        "lat": "35°3′19″N",
        "long": "33°47′4″E"
    },
    {
        "id": 37,
        "url": "https://en.wikipedia.org/wiki/Deryneia",
        "city": "Deryneia",
        "country": "Cyprus",
        "district": "Famagusta",
        "government-mayor": "Andros Karayiannis",
        "population-total": "5,758",
        "time-zone": "UTC+2 (EET)",
        "time-zone-summer-(dst)": "EEST",
        "postal-code": "5380",
        "website": "http://www.deryneia.org.cy",
        "lat": "35°03′20″N",
        "long": "33°57′25″E"
    },
    {
        "id": 38,
        "url": "https://en.wikipedia.org/wiki/Dhekelia_Cantonment",
        "city": "Dhekelia",
        "lat": "35°01′03″N",
        "long": "33°46′24″E"
    },
    {
        "id": 39,
        "url": "https://en.wikipedia.org/wiki/Dhrousha",
        "city": "Dhrousha",
        "country": "Cyprus",
        "district": "Paphos District",
        "elevation": "640 m (2,100 ft)",
        "population-total": "386",
        "time-zone": "UTC+2 (EET)",
        "time-zone-summer-(dst)": "UTC+3 (EEST)",
        "postal-code": "8700",
        "annual-rainfall": "630 mm",
        "lat": "34°57′41″N",
        "long": "32°23′51″E"
    },
    {
        "id": 40,
        "url": "https://en.wikipedia.org/wiki/Episkopi,_Limassol",
        "city": "Episkopi",
        "country": "Cyprus United Kingdom",
        "district": "Limassol District",
        "population-total": "3,681",
        "time-zone": "UTC+2 (EET)",
        "time-zone-summer-(dst)": "UTC+3 (EEST)",
        "website": "www.episkopi.org",
        "lat": "34°40′15″N",
        "long": "32°54′7″E"
    },
    {
        "id": 41,
        "url": "https://en.wikipedia.org/wiki/Ergates",
        "city": "Ergates",
        "country": "Cyprus",
        "district": "Nicosia District",
        "population-total": "1,588",
        "time-zone": "UTC+2 (EET)",
        "time-zone-summer-(dst)": "UTC+3 (EEST)",
        "lat": "35°3′13″N",
        "long": "33°14′34″E"
    },
    {
        "id": 42,
        "url": "https://en.wikipedia.org/wiki/Evrychou",
        "city": "Evrychou",
        "country": "Cyprus",
        "district": "Nicosia District",
        "population-total": "827",
        "time-zone": "UTC+2 (EET)",
        "time-zone-summer-(dst)": "UTC+3 (EEST)",
        "lat": "35°02′N",
        "long": "32°54′E"
    },
    {
        "id": 43,
        "url": "https://en.wikipedia.org/wiki/Fyti",
        "city": "Fyti",
        "country": "Cyprus",
        "district": "Paphos District",
        "elevation": "674 m (2,211 ft)",
        "population-total": "150",
        "lat": "34°55′44″N",
        "long": "32°32′41″E"
    },
    {
        "id": 44,
        "url": "https://en.wikipedia.org/wiki/Galata,_Cyprus",
        "city": "Galata",
        "country": "Cyprus",
        "district": "Nicosia District",
        "population-total": "653",
        "time-zone": "UTC+2 (EET)",
        "time-zone-summer-(dst)": "UTC+3 (EEST)",
        "postal-code": "2827",
        "website": "http://www.galata.org.cy",
        "lat": "34°59′0″N",
        "long": "32°53′0″E"
    },
    {
        "id": 45,
        "url": "https://en.wikipedia.org/wiki/Gerakies",
        "city": "Gerakies",
        "country": "Cyprus",
        "district": "Nicosia District",
        "population-total": "123",
        "time-zone": "UTC+2 (EET)",
        "time-zone-summer-(dst)": "UTC+3 (EEST)",
        "lat": "34°59′59″N",
        "long": "32°48′17″E"
    },
    {
        "id": 46,
        "url": "https://en.wikipedia.org/wiki/Geri_(Cyprus)",
        "city": "Geri",
        "country": "Cyprus",
        "district": "Nicosia District",
        "population-total": "8,235",
        "time-zone": "UTC+2 (EET)",
        "time-zone-summer-(dst)": "UTC+3 (EEST)",
        "website": "www.yeri.org.cy",
        "lat": "35°06′25″N",
        "long": "33°25′17″E"
    },
    {
        "id": 47,
        "url": "https://en.wikipedia.org/wiki/Gerolakkos",
        "city": "Gerolakkos",
        "country": "Cyprus",
        "country-district": "Lefkoşa District",
        "country-country-(de-facto)": "Northern Cyprus",
        "population-total": "2,777",
        "population-municipality": "3,884",
        "time-zone": "UTC+2 (EET)",
        "time-zone-summer-(dst)": "UTC+3 (EEST)",
        "website": "Turkish Cypriot municipality",
        "lat": "35°11′N",
        "long": "33°15′E"
    },
    {
        "id": 48,
        "url": "https://en.wikipedia.org/wiki/Geroskipou",
        "city": "Geroskipou",
        "country": "Cyprus",
        "district": "Paphos District",
        "elevation": "35 m (115 ft)",
        "population-total": "8,313",
        "time-zone": "UTC+2 (EET)",
        "time-zone-summer-(dst)": "UTC+3 (EEST)",
        "postal-code": "8200",
        "website": "http://www.geroskipou-municipality.com",
        "lat": "34°46′N",
        "long": "32°28′E"
    },
    {
        "id": 49,
        "url": "https://en.wikipedia.org/wiki/Gialousa",
        "city": "Gialousa",
        "country": "Cyprus",
        "country-district": "İskele District",
        "country-country-(de-facto)": "Northern Cyprus",
        "government-mayor": "Emrah Yesilirmak",
        "population-total": "1,774",
        "population-municipality": "5,627",
        "website": "Yenierenkoy Turkish municipality",
        "lat": "35°32′08″N",
        "long": "34°11′22″E"
    },
    {
        "id": 50,
        "url": "https://en.wikipedia.org/wiki/Giolou",
        "city": "Giolou",
        "country": "Cyprus",
        "district": "Paphos District",
        "elevation": "305 m (1,001 ft)",
        "population-total": "737",
        "time-zone": "UTC+2 (EET)",
        "time-zone-summer-(dst)": "UTC+3 (EEST)",
        "postal-code": "6331",
        "lat": "34°55′24″N",
        "long": "32°28′28″E"
    },
    {
        "id": 51,
        "url": "https://en.wikipedia.org/wiki/Idalium",
        "city": "Idalium",
        "lat": "35°00′57″N",
        "long": "33°25′23″E"
    },
    {
        "id": 52,
        "url": "https://en.wikipedia.org/wiki/Inia,_Paphos",
        "city": "Inia",
        "country": "Cyprus",
        "district": "Paphos District",
        "elevation": "625 m (2,051 ft)",
        "population": "385",
        "time-zone": "UTC+2 (EET)",
        "time-zone-summer-(dst)": "UTC+3 (EEST)",
        "postal-code": "6352",
        "lat": "34°57′19″N",
        "long": "32°23′37″E"
    },
    {
        "id": 53,
        "url": "https://en.wikipedia.org/wiki/Kaimakli",
        "city": "Kaimakli",
        "country": "Cyprus",
        "country-district": "Nicosia District",
        "country-municipality": "Nicosia",
        "population-total": "11,564",
        "time-zone": "UTC+2 (EET)",
        "time-zone-summer-(dst)": "UTC+3 (EEST)",
        "lat": "35°11′21″N",
        "long": "33°23′1″E"
    },
    {
        "id": 54,
        "url": "https://en.wikipedia.org/wiki/Kakopetria",
        "city": "Kakopetria",
        "country": "Cyprus",
        "district": "Nicosia District",
        "population-total": "1,198",
        "time-zone": "UTC+2 (EET)",
        "time-zone-summer-(dst)": "UTC+3 (EEST)",
        "postal-code": "2800",
        "website": "http://www.kakopetria.org.cy/",
        "lat": "34°59′0″N",
        "long": "32°54′0″E"
    },
    {
        "id": 55,
        "url": "https://en.wikipedia.org/wiki/Kalavasos",
        "city": "Kalavasos",
        "country": "Cyprus",
        "district": "Larnaca District",
        "population-total": "737",
        "time-zone": "UTC+2 (EET)",
        "time-zone-summer-(dst)": "UTC+3 (EEST)",
        "website": "http://www.kalavasos.org/",
        "lat": "34°46′19″N",
        "long": "33°17′45″E"
    },
    {
        "id": 56,
        "url": "https://en.wikipedia.org/wiki/Kalo_Chorio_(%C3%87aml%C4%B1k%C3%B6y)",
        "city": "Kalo Chorio",
        "country": "Cyprus",
        "country-district": "Lefke District",
        "country-country-(de-facto)": "Northern Cyprus",
        "population-total": "170",
        "time-zone": "UTC+2 (EET)",
        "time-zone-summer-(dst)": "UTC+3 (EEST)",
        "lat": "35°6′56″N",
        "long": "32°52′36″E"
    },
    {
        "id": 57,
        "url": "https://en.wikipedia.org/wiki/Kalopanagiotis",
        "city": "Kalopanagiotis",
        "country": "Cyprus",
        "district": "Nicosia District",
        "population-total": "287",
        "time-zone": "UTC+2 (EET)",
        "time-zone-summer-(dst)": "UTC+3 (EEST)",
        "lat": "34°59′31″N",
        "long": "32°49′45″E"
    },
    {
        "id": 58,
        "url": "https://en.wikipedia.org/wiki/Kampia,_Cyprus",
        "city": "Kampia",
        "country": "Cyprus",
        "district": "Nicosia District",
        "population-total": "417",
        "time-zone": "UTC+2 (EET)",
        "time-zone-summer-(dst)": "UTC+3 (EEST)",
        "lat": "35°0′25″N",
        "long": "33°15′22″E"
    },
    {
        "id": 59,
        "url": "https://en.wikipedia.org/wiki/Kampos,_Cyprus",
        "city": "Kampos",
        "country": "Cyprus",
        "district": "Nicosia District",
        "population-total": "426",
        "time-zone": "UTC+2 (EET)",
        "time-zone-summer-(dst)": "UTC+3 (EEST)",
        "lat": "35°2′26″N",
        "long": "32°43′56″E"
    },
    {
        "id": 60,
        "url": "https://en.wikipedia.org/wiki/Kantou,_Cyprus",
        "city": "Kantou",
        "country": "Cyprus",
        "district": "Limassol District",
        "population-total": "397",
        "time-zone": "UTC+2 (EET)",
        "time-zone-summer-(dst)": "UTC+3 (EEST)",
        "lat": "34°41′25″N",
        "long": "32°54′24″E"
    },
    {
        "id": 61,
        "url": "https://en.wikipedia.org/wiki/Kapedes",
        "city": "Kapedes",
        "country": "Cyprus",
        "district": "Nicosia District",
        "population-total": "523",
        "time-zone": "UTC+2 (EET)",
        "time-zone-summer-(dst)": "UTC+3 (EEST)",
        "lat": "34°58′32″N",
        "long": "33°15′14″E"
    },
    {
        "id": 62,
        "url": "https://en.wikipedia.org/wiki/Kato_Deftera",
        "city": "Kato Deftera",
        "country": "Cyprus",
        "district": "Nicosia District",
        "population-total": "2,054",
        "website": "www.deftera.org",
        "lat": "35°05′09″N",
        "long": "33°16′46″E"
    },
    {
        "id": 63,
        "url": "https://en.wikipedia.org/wiki/Kato_Lefkara",
        "city": "Kato Lefkara",
        "country": "Cyprus",
        "district": "Larnaca District",
        "government-type": "Community",
        "population-total": "128",
        "time-zone": "UTC+2 (EET)",
        "time-zone-summer-(dst)": "UTC+3 (EEST)",
        "lat": "34°51′44″N",
        "long": "33°19′0″E"
    },
    {
        "id": 64,
        "url": "https://en.wikipedia.org/wiki/Kato_Zodeia",
        "city": "Kato Zodeia",
        "country": "Cyprus",
        "country-district": "Güzelyurt District",
        "country-country-(de-facto)": "Northern Cyprus",
        "population-total": "3,317",
        "time-zone": "UTC+2 (EET)",
        "time-zone-summer-(dst)": "UTC+3 (EEST)",
        "lat": "35°10′04″N",
        "long": "33°00′26″E"
    },
    {
        "id": 65,
        "url": "https://en.wikipedia.org/wiki/Kellia",
        "city": "Kellia",
        "lat": "30°46′34″N",
        "long": "30°22′08″E"
    },
    {
        "id": 66,
        "url": "https://en.wikipedia.org/wiki/Kelokedara",
        "city": "Kelokedara",
        "country": "Cyprus",
        "district": "Paphos District",
        "population-total": "227",
        "time-zone": "UTC+2 (EET)",
        "time-zone-summer-(dst)": "UTC+3 (EEST)",
        "postal-code": "6210",
        "lat": "34°48′45″N",
        "long": "32°39′3″E"
    },
    {
        "id": 67,
        "url": "https://en.wikipedia.org/wiki/Kissonerga",
        "city": "Kissonerga",
        "country": "Cyprus",
        "district": "Paphos District",
        "elevation": "112 m (367 ft)",
        "population-total": "2,505",
        "time-zone": "UTC+2 (EET)",
        "time-zone-summer-(dst)": "UTC+3 (EEST)",
        "postal-code": "8574",
        "lat": "34°49′N",
        "long": "32°24′E"
    },
    {
        "id": 68,
        "url": "https://en.wikipedia.org/wiki/Kiti,_Cyprus",
        "city": "Kiti",
        "country": "Cyprus",
        "district": "Larnaca District",
        "population-total": "4,252",
        "time-zone": "UTC+2 (EET)",
        "time-zone-summer-(dst)": "UTC+3 (EEST)",
        "lat": "34°50′50″N",
        "long": "33°34′19″E"
    },
    {
        "id": 69,
        "url": "https://en.wikipedia.org/wiki/Kofinou",
        "city": "Kofinou",
        "country": "Cyprus",
        "district": "Larnaca District",
        "population-total": "1,312",
        "time-zone": "UTC+2 (EET)",
        "time-zone-summer-(dst)": "UTC+3 (EEST)",
        "lat": "34°49′33″N",
        "long": "33°23′30″E"
    },
    {
        "id": 70,
        "url": "https://en.wikipedia.org/wiki/Koilani",
        "city": "Koilani",
        "country": "Cyprus",
        "district": "Limassol District",
        "government-president-of-community-council": "Michalakis Pisis",
        "elevation": "2,690 ft (820 m)",
        "population-total": "280",
        "time-zone": "UTC+2 (EET)",
        "time-zone-summer-(dst)": "UTC+3 (EEST)",
        "postal-code": "4776",
        "website": "Official Koilani Village Website",
        "lat": "34°50′41″N",
        "long": "32°51′37″E"
    },
    {
        "id": 71,
        "url": "https://en.wikipedia.org/wiki/Kokkina",
        "city": "Kokkina",
        "country": "Cyprus",
        "country-district": "Lefke District",
        "country-country-(de-facto)": "Northern Cyprus",
        "lat": "35°10′45″N",
        "long": "32°36′42″E"
    },
    {
        "id": 72,
        "url": "https://en.wikipedia.org/wiki/Kormakitis",
        "city": "Kormakitis",
        "country": "Cyprus",
        "country-district": "Kyrenia District",
        "elevation": "168 m (551 ft)",
        "population-total": "309",
        "lat": "35°20′34″N",
        "long": "33°00′39″E"
    },
    {
        "id": 73,
        "url": "https://en.wikipedia.org/wiki/Kornokipos",
        "city": "Kornokipos",
        "country": "Cyprus",
        "country-district": "Gazimağusa District",
        "country-country-(de-facto)": "Northern Cyprus",
        "population-total": "500",
        "time-zone": "UTC+2 (EET)",
        "time-zone-summer-(dst)": "UTC+3 (EEST)",
        "lat": "35°16′57″N",
        "long": "33°34′22″E"
    },
    {
        "id": 74,
        "url": "https://en.wikipedia.org/wiki/Kornos,_Cyprus",
        "city": "Kornos",
        "country": "Cyprus",
        "district": "Larnaca District",
        "population-total": "2,083",
        "time-zone": "UTC+2 (EET)",
        "time-zone-summer-(dst)": "UTC+3 (EEST)",
        "website": "www.kornos.org",
        "lat": "34°55′18″N",
        "long": "33°23′44″E"
    },
    {
        "id": 75,
        "url": "https://en.wikipedia.org/wiki/Kouklia",
        "city": "Kouklia",
        "country": "Cyprus",
        "district": "Paphos District",
        "government-mayor": "Michael S. Solonos",
        "government-": "669",
        "time-zone": "UTC+2 (EET)",
        "time-zone-summer-(dst)": "UTC+3 (EEST)",
        "postcode": "8500",
        "website": "www.Kouklia.org.cy",
        "official-name": "Paphos",
        "criteria": "Cultural: iii, vi",
        "reference": "79",
        "inscription": "1980 (4th Session)",
        "area": "162.0171 ha",
        "lat": "34°41′52″N",
        "long": "32°35′31″E"
    },
    {
        "id": 76,
        "url": "https://en.wikipedia.org/wiki/Kyperounta",
        "city": "Kyperounta",
        "country": "Cyprus",
        "district": "Limassol District",
        "population-total": "1,497",
        "time-zone": "UTC+2 (EET)",
        "time-zone-summer-(dst)": "UTC+3 (EEST)",
        "lat": "34°56′29″N",
        "long": "32°58′9″E"
    },
    {
        "id": 77,
        "url": "https://en.wikipedia.org/wiki/Kythrea",
        "city": "Kythrea",
        "country": "Cyprus",
        "country-district": "Lefkoşa District",
        "country-country-(de-facto)": "Northern Cyprus",
        "government-mayor": "Ali Karavezirler (CTP)",
        "government-mayor-in-exile": "Petros M. Kareklas",
        "population-total": "3,284",
        "population-municipality": "17,213",
        "website": "Greek Cypriot municipality (in exile)Turkish Cypriot municipality",
        "lat": "35°15′N",
        "long": "33°29′E"
    },
    {
        "id": 78,
        "url": "https://en.wikipedia.org/wiki/Lagoudera",
        "city": "Lagoudera",
        "country": "Cyprus",
        "district": "Nicosia District",
        "population-total": "84",
        "time-zone": "UTC+2 (EET)",
        "time-zone-summer-(dst)": "UTC+3 (EEST)",
        "lat": "34°57′45″N",
        "long": "33°0′37″E"
    },
    {
        "id": 79,
        "url": "https://en.wikipedia.org/wiki/Lapithos",
        "city": "Lambousa",
        "country": "Cyprus",
        "country-district": "Girne District",
        "country-country-(de-facto)": "Northern Cyprus",
        "government-mayor": "Mustafa Aktuğ (in Lapithos) Neoptolemos Kotsapa (in exile)",
        "population-total": "7,839",
        "time-zone": "UTC+2 (EET)",
        "time-zone-summer-(dst)": "UTC+3 (EEST)",
        "climate": "Csa",
        "website": "Turkish-Cypriot municipalityCypriot municipality (in exile)",
        "lat": "35°20′12″N",
        "long": "33°10′27″E"
    },
    {
        "id": 80,
        "url": "https://en.wikipedia.org/wiki/Lapithos",
        "city": "Lapithos",
        "country": "Cyprus",
        "country-district": "Girne District",
        "country-country-(de-facto)": "Northern Cyprus",
        "government-mayor": "Mustafa Aktuğ (in Lapithos) Neoptolemos Kotsapa (in exile)",
        "population-total": "7,839",
        "time-zone": "UTC+2 (EET)",
        "time-zone-summer-(dst)": "UTC+3 (EEST)",
        "climate": "Csa",
        "website": "Turkish-Cypriot municipalityCypriot municipality (in exile)",
        "lat": "35°20′12″N",
        "long": "33°10′27″E"
    },
    {
        "id": 81,
        "url": "https://en.wikipedia.org/wiki/Latsia",
        "city": "Latsia",
        "country": "Cyprus",
        "district": "Nicosia District",
        "population-total": "16,774",
        "time-zone": "UTC+2 (EET)",
        "time-zone-summer-(dst)": "UTC+3 (EEST)",
        "website": "http://www.latsia.org.cy",
        "lat": "35°06′N",
        "long": "33°22′E"
    },
    {
        "id": 82,
        "url": "https://en.wikipedia.org/wiki/Lefka",
        "city": "Lefka",
        "country": "Cyprus",
        "country-district": "Lefke District",
        "country-country-(de-facto)": "Northern Cyprus",
        "government-mayor": "Aziz Kaya (CTP)",
        "population-total": "3,009",
        "population-municipality": "11,091",
        "time-zone": "UTC+2 (EET)",
        "time-zone-summer-(dst)": "UTC+3 (EEST)",
        "website": "Lefka Turkish Municipality",
        "lat": "35°6′48″N",
        "long": "32°51′4″E"
    },
    {
        "id": 83,
        "url": "https://en.wikipedia.org/wiki/Lefkoniko",
        "city": "Lefkoniko",
        "country": "Cyprus",
        "country-district": "Gazimağusa District",
        "country-country-(de-facto)": "Northern Cyprus",
        "government-mayor": "Hasan Öztaş (in Lefkoniko)  Zina Lisandrou Panagidi (in exile)",
        "population-total": "1,253",
        "population-municipality": "2,380",
        "website": "Turkish Cypriot municipality",
        "lat": "35°15′36″N",
        "long": "33°43′54″E"
    },
    {
        "id": 84,
        "url": "https://en.wikipedia.org/wiki/Leonarisso",
        "city": "Leonarisso",
        "country": "Cyprus",
        "country-district": "İskele District",
        "country-country-(de-facto)": "Northern Cyprus",
        "government-mukhtar": "Hacıbey Mehmetoğlu",
        "population-total": "739",
        "time-zone": "UTC+2 (EET)",
        "time-zone-summer-(dst)": "UTC+3 (EEST)",
        "lat": "35°28′11″N",
        "long": "34°8′19″E"
    },
    {
        "id": 85,
        "url": "https://en.wikipedia.org/wiki/Limnitis",
        "city": "Limnitis",
        "country": "Cyprus",
        "country-district": "Lefke District",
        "country-country-(de-facto)": "Northern Cyprus",
        "population-total": "458",
        "time-zone": "UTC+2 (EET)",
        "time-zone-summer-(dst)": "UTC+3 (EEST)",
        "lat": "35°10′02″N",
        "long": "32°44′17″E"
    },
    {
        "id": 86,
        "url": "https://en.wikipedia.org/wiki/Louroujina",
        "city": "Louroujina",
        "country": "Cyprus",
        "country-district": "Lefkoşa District",
        "country-country-(de-facto)": "Northern Cyprus",
        "government-mayor": "Hasan Barbaros",
        "population-total": "390",
        "website": "Akincilar Turkish municipality  The municipality in NC eGov portal",
        "lat": "35°00′33″N",
        "long": "33°27′53″E"
    },
    {
        "id": 87,
        "url": "https://en.wikipedia.org/wiki/Lythrangomi",
        "city": "Lythrangomi",
        "country": "Cyprus",
        "country-district": "İskele District",
        "country-country-(de-facto)": "Northern Cyprus",
        "government-mukhtar": "Sefer Mani",
        "population-total": "228",
        "time-zone": "UTC+2 (EET)",
        "time-zone-summer-(dst)": "UTC+3 (EEST)",
        "lat": "35°28′36″N",
        "long": "34°10′1″E"
    },
    {
        "id": 88,
        "url": "https://en.wikipedia.org/wiki/Lythrodontas",
        "city": "Lythrodontas",
        "country": "Cyprus",
        "district": "Nicosia District",
        "population-total": "2,628",
        "time-zone": "UTC+2 (EET)",
        "time-zone-summer-(dst)": "UTC+3 (EEST)",
        "lat": "34°56′59″N",
        "long": "33°17′46″E"
    },
    {
        "id": 89,
        "url": "https://en.wikipedia.org/wiki/Lysi",
        "city": "Lysi",
        "country": "Cyprus",
        "country-district": "Gazimağusa District",
        "country-country-(de-facto)": "Northern Cyprus",
        "government-mayor": "Ahmet Latif",
        "population-total": "2,471",
        "time-zone": "UTC+2 (EET)",
        "time-zone-summer-(dst)": "UTC+3 (EEST)",
        "website": "Turkish Cypriot municipality",
        "lat": "35°6′19″N",
        "long": "33°40′52″E"
    },
    {
        "id": 90,
        "url": "https://en.wikipedia.org/wiki/Malounta",
        "city": "Malounta",
        "country": "Cyprus",
        "district": "Nicosia District",
        "population-total": "402",
        "time-zone": "UTC+2 (EET)",
        "time-zone-summer-(dst)": "UTC+3 (EEST)",
        "lat": "35°2′4″N",
        "long": "33°10′55″E"
    },
    {
        "id": 91,
        "url": "https://en.wikipedia.org/wiki/Mammari",
        "city": "Mammari",
        "country": "Cyprus",
        "district": "Nicosia District",
        "government-mayor": "Odysseas Koumoulis",
        "population-total": "1,052",
        "time-zone": "UTC+2 (EET)",
        "time-zone-summer-(dst)": "UTC+3 (EEST)",
        "lat": "35°10′27″N",
        "long": "33°12′10″E"
    },
    {
        "id": 92,
        "url": "https://en.wikipedia.org/wiki/Mandria,_Limassol",
        "city": "Mandria, Limassol",
        "country": "Cyprus",
        "district": "Limassol District",
        "population-total": "700",
        "time-zone": "UTC+2 (EET)",
        "time-zone-summer-(dst)": "UTC+3 (EEST)",
        "website": "http://www.mandria.org/",
        "lat": "34°52′9″N",
        "long": "32°49′55″E"
    },
    {
        "id": 93,
        "url": "https://en.wikipedia.org/wiki/Mandria,_Paphos",
        "city": "Mandria, Paphos",
        "country": "Cyprus",
        "district": "Paphos District",
        "population-total": "360",
        "time-zone": "UTC+2 (EET)",
        "time-zone-summer-(dst)": "UTC+3 (EEST)",
        "postal-code": "8504",
        "lat": "34°42′55″N",
        "long": "32°31′54″E"
    },
    {
        "id": 94,
        "url": "https://en.wikipedia.org/wiki/Margo,_Nicosia",
        "city": "Margo",
        "country": "Cyprus",
        "country-district": "Lefkoşa District",
        "country-country-(de-facto)": "Northern Cyprus",
        "time-zone": "UTC+2 (EET)",
        "time-zone-summer-(dst)": "UTC+3 (EEST)",
        "lat": "35°4′39″N",
        "long": "33°29′29″E"
    },
    {
        "id": 95,
        "url": "https://en.wikipedia.org/wiki/Maroni,_Cyprus",
        "city": "Maroni",
        "country": "Cyprus",
        "district": "Larnaca District",
        "population-total": "710",
        "time-zone": "UTC+2 (EET)",
        "time-zone-summer-(dst)": "UTC+3 (EEST)",
        "website": "http://www.maroni.org.cy",
        "lat": "34°45′26″N",
        "long": "33°21′21″E"
    },
    {
        "id": 96,
        "url": "https://en.wikipedia.org/wiki/Mathiatis",
        "city": "Mathiatis",
        "country": "Cyprus",
        "district": "Nicosia District",
        "population-total": "646",
        "time-zone": "UTC+2 (EET)",
        "time-zone-summer-(dst)": "UTC+3 (EEST)",
        "lat": "34°57′46″N",
        "long": "33°20′10″E"
    },
    {
        "id": 97,
        "url": "https://en.wikipedia.org/wiki/Melini",
        "city": "Melini",
        "country": "Cyprus",
        "district": "Larnaca District",
        "population-total": "59",
        "time-zone": "UTC+2 (EET)",
        "time-zone-summer-(dst)": "UTC+3 (EEST)",
        "lat": "34°51′59″N",
        "long": "33°9′23″E"
    },
    {
        "id": 98,
        "url": "https://en.wikipedia.org/wiki/Meniko",
        "city": "Meniko",
        "country": "Cyprus",
        "district": "Nicosia District",
        "population-total": "980",
        "time-zone": "UTC+2 (EET)",
        "time-zone-summer-(dst)": "UTC+3 (EEST)",
        "lat": "35°6′44″N",
        "long": "33°8′46″E"
    },
    {
        "id": 99,
        "url": "https://en.wikipedia.org/wiki/Mia_Milia",
        "city": "Mia Milia",
        "country": "Cyprus",
        "country-district": "Lefkoşa District",
        "country-country-(de-facto)": "Northern Cyprus",
        "population-total": "4,204",
        "lat": "35°12′17.77″N",
        "long": "33°25′17.34″E"
    },
    {
        "id": 100,
        "url": "https://en.wikipedia.org/wiki/Milia,_Famagusta",
        "city": "Milia",
        "country": "Cyprus",
        "country-district": "Gazimağusa District",
        "country-country-(de-facto)": "Northern Cyprus",
        "time-zone": "UTC+2 (EET)",
        "time-zone-summer-(dst)": "UTC+3 (EEST)",
        "lat": "35°14′22″N",
        "long": "33°46′54″E"
    },
    {
        "id": 101,
        "url": "https://en.wikipedia.org/wiki/Miliou",
        "city": "Miliou",
        "country": "Cyprus",
        "district": "Paphos District",
        "elevation": "252 m (827 ft)",
        "population-total": "81",
        "time-zone": "UTC+2 (EET)",
        "time-zone-summer-(dst)": "UTC+3 (EEST)",
        "lat": "34°56′N",
        "long": "32°28′E"
    },
    {
        "id": 102,
        "url": "https://en.wikipedia.org/wiki/Morphou",
        "city": "Morphou",
        "country": "Cyprus",
        "country-district": "Güzelyurt District",
        "country-country-(de-facto)": "Northern Cyprus",
        "government-mayor": "Mahmut Özçınar",
        "population-total": "24,070",
        "time-zone": "UTC+2 (EET)",
        "time-zone-summer-(dst)": "UTC+3 (EEST)",
        "website": "Municipality of Güzelyurt",
        "lat": "35°11′53″N",
        "long": "32°59′38″E"
    },
    {
        "id": 103,
        "url": "https://en.wikipedia.org/wiki/Moutoullas",
        "city": "Moutoullas",
        "country": "Cyprus",
        "district": "Nicosia District",
        "elevation": "800 m (2,600 ft)",
        "population-total": "174",
        "time-zone": "UTC+2 (EET)",
        "time-zone-summer-(dst)": "UTC+3 (EEST)",
        "postal-code": "2866",
        "website": "moutoullas.com.cy",
        "lat": "34°59′N",
        "long": "32°49′E"
    },
    {
        "id": 104,
        "url": "https://en.wikipedia.org/wiki/Mylikouri",
        "city": "Mylikouri",
        "country": "Cyprus",
        "district": "Nicosia District",
        "population-total": "39",
        "time-zone": "UTC+2 (EET)",
        "time-zone-summer-(dst)": "UTC+3 (EEST)",
        "lat": "34°57′43″N",
        "long": "32°45′2″E"
    },
    {
        "id": 105,
        "url": "https://en.wikipedia.org/wiki/Nata,_Cyprus",
        "city": "Nata",
        "country": "Cyprus",
        "district": "Paphos District",
        "population-total": "181",
        "lat": "34°46′N",
        "long": "32°34′E"
    },
    {
        "id": 106,
        "url": "https://en.wikipedia.org/wiki/Oikos,_Cyprus",
        "city": "Oikos",
        "country": "Cyprus",
        "district": "Nicosia District",
        "population-total": "186",
        "time-zone": "UTC+2 (EET)",
        "time-zone-summer-(dst)": "UTC+3 (EEST)",
        "postal-code": "2867",
        "lat": "34°59′58″N",
        "long": "32°49′49″E"
    },
    {
        "id": 107,
        "url": "https://en.wikipedia.org/wiki/Omorphita",
        "city": "Omorphita",
        "country": "Cyprus",
        "country-district": "Lefkoşa District",
        "country-municipality": "Nicosia Turkish Municipality",
        "country-country-(controlled-by)": "Northern Cyprus",
        "population-total": "10,856",
        "time-zone": "UTC+2 (EET)",
        "time-zone-summer-(dst)": "UTC+3 (EEST)",
        "lat": "35°11′30″N",
        "long": "33°22′30″E"
    },
    {
        "id": 108,
        "url": "https://en.wikipedia.org/wiki/Ormideia",
        "city": "Ormideia",
        "country": "Cyprus",
        "district": "Larnaca District",
        "population-total": "4,189",
        "time-zone": "UTC+2 (EET)",
        "time-zone-summer-(dst)": "UTC+3 (EEST)",
        "lat": "34°59′33″N",
        "long": "33°46′49″E"
    },
    {
        "id": 109,
        "url": "https://en.wikipedia.org/wiki/Oroklini",
        "city": "Oroklini",
        "country": "Cyprus",
        "district": "Larnaca District",
        "government-type": "Community",
        "government-council-president": "Neophytos Facontes",
        "population-total": "6,134",
        "time-zone": "UTC+2 (EET)",
        "time-zone-summer-(dst)": "UTC+3 (EEST)",
        "website": "http://www.voroklini.org/",
        "lat": "34°58′58″N",
        "long": "33°39′16″E"
    },
    {
        "id": 110,
        "url": "https://en.wikipedia.org/wiki/Orounta",
        "city": "Orounta",
        "country": "Cyprus",
        "district": "Nicosia District",
        "population-total": "656",
        "time-zone": "UTC+2 (EET)",
        "time-zone-summer-(dst)": "UTC+3 (EEST)",
        "lat": "35°6′5″N",
        "long": "33°5′38″E"
    },
    {
        "id": 111,
        "url": "https://en.wikipedia.org/wiki/Pachna",
        "city": "Pachna",
        "country": "Cyprus",
        "district": "Limassol District",
        "government-mayor": "Andreas Savva",
        "elevation": "745 m (2,444 ft)",
        "population-total": "865",
        "time-zone": "UTC+2 (EET)",
        "time-zone-summer-(dst)": "UTC+3 (EEST)",
        "postal-code": "4700",
        "website": "http://www.pachnavillage.com",
        "lat": "34°46′42″N",
        "long": "32°47′35″E"
    },
    {
        "id": 112,
        "url": "https://en.wikipedia.org/wiki/Palaichori_Morphou",
        "city": "Palaichori Morphou",
        "country": "Cyprus",
        "district": "Nicosia District",
        "elevation": "2,251 ft (686 m)",
        "population-total": "1,196",
        "time-zone": "UTC+2 (EET)",
        "time-zone-summer-(dst)": "UTC+3 (EEST)",
        "website": "www.palaichori.org",
        "lat": "34°55′25″N",
        "long": "33°05′28″E"
    },
    {
        "id": 113,
        "url": "https://en.wikipedia.org/wiki/Palaichori_Oreinis",
        "city": "Palaichori Oreinis",
        "country": "Cyprus",
        "district": "Nicosia District",
        "elevation": "2,251 ft (686 m)",
        "population-total": "333",
        "time-zone": "UTC+2 (EET)",
        "time-zone-summer-(dst)": "UTC+3 (EEST)",
        "website": "www.palaichori.org",
        "lat": "34°55′19″N",
        "long": "33°05′38″E"
    },
    {
        "id": 114,
        "url": "https://en.wikipedia.org/wiki/Panagia,_Cyprus",
        "city": "Panagia",
        "country": "Cyprus",
        "district": "Pafos District",
        "elevation": "900 m (3,000 ft)",
        "population-total": "564",
        "time-zone": "UTC+2 (EET)",
        "time-zone-summer-(dst)": "UTC+3 (EEST)",
        "website": "http://www.PanayiaVillage.com",
        "lat": "34°55′N",
        "long": "32°38′E"
    },
    {
        "id": 115,
        "url": "https://en.wikipedia.org/wiki/Pano_Deftera",
        "city": "Pano Deftera",
        "country": "Cyprus",
        "district": "Nicosia District",
        "population-total": "2,789",
        "website": "www.deftera.org",
        "lat": "35°04′50″N",
        "long": "33°15′58″E"
    },
    {
        "id": 116,
        "url": "https://en.wikipedia.org/wiki/Pano_Zodeia",
        "city": "Pano Zodeia",
        "country": "Cyprus",
        "country-district": "Güzelyurt District",
        "country-country-(de-facto)": "Northern Cyprus",
        "time-zone": "UTC+2 (EET)",
        "time-zone-summer-(dst)": "UTC+3 (EEST)",
        "lat": "35°09′49″N",
        "long": "33°00′57″E"
    },
    {
        "id": 117,
        "url": "https://en.wikipedia.org/wiki/Pano_Lefkara",
        "city": "Pano Lefkara",
        "country": "Cyprus",
        "district": "Larnaca District",
        "elevation": "500 m (1,600 ft)",
        "population-total": "1,100",
        "time-zone": "UTC+2 (EET)",
        "time-zone-summer-(dst)": "UTC+3 (EEST)",
        "postal-code": "7710",
        "website": "http://www.lefkara.org.cy/",
        "lat": "34°52′N",
        "long": "33°18′E"
    },
    {
        "id": 118,
        "url": "https://en.wikipedia.org/wiki/Paralimni",
        "city": "Paralimni",
        "country": "Cyprus",
        "district": "Famagusta District",
        "government-mayor": "Theodoros Pyrillis",
        "population-total": "40,000",
        "time-zone": "UTC+2 (EET)",
        "time-zone-summer-(dst)": "UTC+3 (EEST)",
        "postal-code": "5280-5297",
        "website": "www.paralimni.org.cy",
        "lat": "35°2′0″N",
        "long": "33°59′0″E"
    },
    {
        "id": 119,
        "url": "https://en.wikipedia.org/wiki/Pedoulas",
        "city": "Pedoulas",
        "country": "Cyprus",
        "district": "Nicosia District",
        "population-total": "132",
        "time-zone": "UTC+2 (EET)",
        "time-zone-summer-(dst)": "UTC+3 (EEST)",
        "postal-code": "2850",
        "website": "http://pedoulasvillage.com",
        "lat": "34°58′3″N",
        "long": "32°49′43″E"
    },
    {
        "id": 120,
        "url": "https://en.wikipedia.org/wiki/Pegeia",
        "city": "Pegeia",
        "country": "Cyprus",
        "district": "Paphos District",
        "government-mayor": "Marinos Lambrou",
        "population-total": "12,356",
        "population-density": "120/sq mi (48/km)",
        "time-zone": "UTC+2 (EET)",
        "time-zone-summer-(dst)": "UTC+3 (EEST)",
        "postal-code": "8560",
        "website": "www.pegeiamunicipality.com",
        "lat": "34°53′0″N",
        "long": "32°23′0″E"
    },
    {
        "id": 121,
        "url": "https://en.wikipedia.org/wiki/Pera_Chorio",
        "city": "Pera Chorio",
        "country": "Cyprus",
        "district": "Nicosia District",
        "population-total": "2,236",
        "time-zone": "UTC+2 (EET)",
        "time-zone-summer-(dst)": "UTC+3 (EEST)",
        "website": "http://www.perachorio-nissou.org.cy/en/page/home",
        "lat": "35°0′42″N",
        "long": "33°23′25″E"
    },
    {
        "id": 122,
        "url": "https://en.wikipedia.org/wiki/Pera_Orinis",
        "city": "Pera Orinis",
        "country": "Cyprus",
        "district": "Nicosia District",
        "population-total": "1,018",
        "time-zone": "UTC+2 (EET)",
        "time-zone-summer-(dst)": "UTC+3 (EEST)",
        "lat": "35°1′56″N",
        "long": "33°15′11″E"
    },
    {
        "id": 123,
        "url": "https://en.wikipedia.org/wiki/Pera_Pedi",
        "city": "Pera Pedi",
        "country": "Cyprus",
        "district": "Limassol",
        "population-total": "66",
        "time-zone": "UTC+2 (EET)",
        "time-zone-summer-(dst)": "UTC+3 (EEST)",
        "lat": "34°51′34″N",
        "long": "32°52′34″E"
    },
    {
        "id": 124,
        "url": "https://en.wikipedia.org/wiki/Peristerona",
        "city": "Peristerona",
        "country": "Cyprus",
        "district": "Nicosia District",
        "elevation": "1,339 ft (408 m)",
        "population-total": "2,173",
        "time-zone": "UTC+2 (EET)",
        "time-zone-summer-(dst)": "UTC+3 (EEST)",
        "lat": "35°7′44″N",
        "long": "33°4′45″E"
    },
    {
        "id": 125,
        "url": "https://en.wikipedia.org/wiki/Peristeronopigi",
        "city": "Peristeronopigi",
        "country": "Cyprus",
        "country-district": "Gazimağusa District",
        "country-country-(de-facto)": "Northern Cyprus",
        "population-total": "860",
        "lat": "35°13′13″N",
        "long": "33°45′36″E"
    },
    {
        "id": 126,
        "url": "https://en.wikipedia.org/wiki/Pissouri",
        "city": "Pissouri",
        "country": "Cyprus",
        "district": "Limassol District",
        "government-mayor": "Lazaros Lazarou",
        "government-executive-director": "Petros Foutas",
        "population-total": "1,033",
        "time-zone": "UTC+2 (EET)",
        "time-zone-summer-(dst)": "UTC+3 (EEST)",
        "postal-code": "4607",
        "website": "http://www.pissouri.com/",
        "lat": "34°40′N",
        "long": "32°42′E"
    },
    {
        "id": 127,
        "url": "https://en.wikipedia.org/wiki/Platanistasa",
        "city": "Platanistasa",
        "country": "Cyprus",
        "district": "Nicosia District",
        "elevation": "3,120 ft (950 m)",
        "population-total": "172",
        "time-zone": "UTC+2 (EET)",
        "time-zone-summer-(dst)": "UTC+3 (EEST)",
        "website": "http://www.platanistasa.org/",
        "lat": "34°56′47″N",
        "long": "33°2′41″E"
    },
    {
        "id": 128,
        "url": "https://en.wikipedia.org/wiki/Platres",
        "city": "Platres",
        "country": "Cyprus",
        "district": "Limassol",
        "elevation": "1,200 m (3,900 ft)",
        "population-total": "280",
        "time-zone": "UTC+2 (EET)",
        "postal-code": "CY-4820",
        "website": "http://www.platres.org.cy",
        "lat": "34°53′13″N",
        "long": "32°51′46″E"
    },
    {
        "id": 129,
        "url": "https://en.wikipedia.org/wiki/Polis,_Cyprus",
        "city": "Polis",
        "country": "Cyprus",
        "district": "Paphos District",
        "government-mayor": "Yiotis Papachristofi",
        "population-total": "3,690",
        "time-zone": "UTC+2 (EET)",
        "time-zone-summer-(dst)": "UTC+3 (EEST)",
        "lat": "35°2′0″N",
        "long": "32°26′0″E"
    },
    {
        "id": 130,
        "url": "https://en.wikipedia.org/wiki/Politiko",
        "city": "Politiko",
        "country": "Cyprus",
        "district": "Nicosia District",
        "population-total": "369",
        "time-zone": "UTC+2 (EET)",
        "time-zone-summer-(dst)": "UTC+3 (EEST)",
        "lat": "35°1′40″N",
        "long": "33°14′31″E"
    },
    {
        "id": 131,
        "url": "https://en.wikipedia.org/wiki/Polystypos",
        "city": "Polystypos",
        "country": "Cyprus",
        "district": "Nicosia District",
        "population-total": "173",
        "time-zone": "UTC+2 (EET)",
        "time-zone-summer-(dst)": "UTC+3 (EEST)",
        "website": "http://www.polystipos.org/",
        "lat": "34°56′22″N",
        "long": "33°1′10″E"
    },
    {
        "id": 132,
        "url": "https://en.wikipedia.org/wiki/Pomos",
        "city": "Pomos",
        "country": "Cyprus",
        "district": "Paphos District",
        "population-total": "595",
        "time-zone": "UTC+2 (EET)",
        "time-zone-summer-(dst)": "UTC+3 (EEST)",
        "postal-code": "6367",
        "lat": "35°9′35″N",
        "long": "32°32′42″E"
    },
    {
        "id": 133,
        "url": "https://en.wikipedia.org/wiki/Potamos_tou_Kampou",
        "city": "Potamos tou Kampou",
        "country": "Cyprus",
        "country-district": "Lefke District",
        "country-country-(de-facto)": "Northern Cyprus",
        "population-total": "669",
        "time-zone": "UTC+2 (EET)",
        "time-zone-summer-(dst)": "UTC+3 (EEST)",
        "lat": "35°08′39″N",
        "long": "32°48′28″E"
    },
    {
        "id": 134,
        "url": "https://en.wikipedia.org/wiki/Protaras",
        "city": "Protaras",
        "country": "Cyprus",
        "district": "Famagusta District",
        "population-total": "20,230",
        "time-zone": "UTC+2 (EET)",
        "time-zone-summer-(dst)": "UTC+3 (EEST)",
        "lat": "35°0′54″N",
        "long": "34°3′15″E"
    },
    {
        "id": 135,
        "url": "https://en.wikipedia.org/wiki/Psimolofou",
        "city": "Psimolofou",
        "country": "Cyprus",
        "district": "Nicosia District",
        "population-total": "1,686",
        "time-zone": "UTC+2 (EET)",
        "time-zone-summer-(dst)": "UTC+3 (EEST)",
        "lat": "35°3′38″N",
        "long": "33°15′36″E"
    },
    {
        "id": 136,
        "url": "https://en.wikipedia.org/wiki/Pyla",
        "city": "Pyla",
        "country": "Cyprus",
        "district": "Larnaca District",
        "population-total": "2,771",
        "time-zone": "UTC+2 (EET)",
        "time-zone-summer-(dst)": "UTC+3 (EEST)",
        "lat": "35°00′50″N",
        "long": "33°41′33″E"
    },
    {
        "id": 137,
        "url": "https://en.wikipedia.org/wiki/Pyrgos,_Limassol",
        "city": "Pyrgos",
        "country": "Cyprus",
        "district": "Limassol District",
        "population-total": "1,348",
        "time-zone": "UTC+2 (EET)",
        "time-zone-summer-(dst)": "UTC+3 (EEST)",
        "website": "http://www.pyrgos.org/",
        "lat": "34°44′34″N",
        "long": "33°11′0″E"
    },
    {
        "id": 138,
        "url": "https://en.wikipedia.org/wiki/Rizokarpaso",
        "city": "Rizokarpaso",
        "country": "Cyprus",
        "country-district": "İskele District",
        "country-country-(de-facto)": "Northern Cyprus",
        "government-mayor": "Suphi Coşkun (CTP)",
        "population-total": "2,349",
        "time-zone": "UTC+2 (EET)",
        "time-zone-summer-(dst)": "UTC+3 (EEST)",
        "lat": "35°35′55″N",
        "long": "34°22′50″E"
    },
    {
        "id": 139,
        "url": "https://en.wikipedia.org/wiki/Silikou",
        "city": "Silikou",
        "country": "Cyprus",
        "district": "Limassol District",
        "population-total": "98",
        "time-zone": "UTC+2 (EET)",
        "time-zone-summer-(dst)": "UTC+3 (EEST)",
        "lat": "34°49′56″N",
        "long": "32°53′20″E"
    },
    {
        "id": 140,
        "url": "https://en.wikipedia.org/wiki/Sotira,_Famagusta",
        "city": "Sotira, Famagusta",
        "country": "Cyprus",
        "district": "Famagusta District",
        "population-total": "5,474",
        "website": "www.sotira.org.cy",
        "lat": "35°01′36″N",
        "long": "33°57′01″E"
    },
    {
        "id": 141,
        "url": "https://en.wikipedia.org/wiki/Sotira,_Limassol",
        "city": "Sotira, Limassol",
        "country": "Cyprus",
        "district": "Limassol District",
        "population-total": "83",
        "time-zone": "UTC+2 (EET)",
        "time-zone-summer-(dst)": "UTC+3 (EEST)",
        "lat": "34°42′44″N",
        "long": "32°51′47″E"
    },
    {
        "id": 142,
        "url": "https://en.wikipedia.org/wiki/Strovolos",
        "city": "Strovolos",
        "country": "Cyprus",
        "district": "Nicosia District",
        "government-mayor": "Andreas Papacharalambous",
        "population-total": "67,904",
        "time-zone": "UTC+2 (EET)",
        "time-zone-summer-(dst)": "UTC+3 (EEST)",
        "website": "strovolos.org.cy",
        "lat": "35°09′N",
        "long": "33°20′E"
    },
    {
        "id": 143,
        "url": "https://en.wikipedia.org/wiki/Templos",
        "city": "Templos",
        "country": "Cyprus",
        "country-district": "Girne District",
        "country-country-(de-facto)": "Northern Cyprus",
        "population-total": "1,090",
        "time-zone": "UTC+2 (EET)",
        "time-zone-summer-(dst)": "UTC+3 (EEST)",
        "lat": "35°19′52″N",
        "long": "33°17′39″E"
    },
    {
        "id": 144,
        "url": "https://en.wikipedia.org/wiki/Trikomo,_Cyprus",
        "city": "Trikomo",
        "country": "Cyprus",
        "country-district": "İskele District",
        "country-country-(de-facto)": "Northern Cyprus",
        "government-mayor": "Hasan Sadıkoğlu (UBP)",
        "population-total": "1,948",
        "population-municipality": "7,906",
        "time-zone": "UTC+2 (EET)",
        "time-zone-summer-(dst)": "UTC+3 (EEST)",
        "climate": "Csa",
        "website": "İskele Municipality",
        "lat": "35°17′15″N",
        "long": "33°53′30″E"
    },
    {
        "id": 145,
        "url": "https://en.wikipedia.org/wiki/Troulloi",
        "city": "Troulloi",
        "country": "Cyprus",
        "district": "Larnaca District",
        "population-total": "1,175",
        "time-zone": "UTC+2 (EET)",
        "time-zone-summer-(dst)": "UTC+3 (EEST)",
        "lat": "35°1′55″N",
        "long": "33°36′54″E"
    },
    {
        "id": 146,
        "url": "https://en.wikipedia.org/wiki/Tsakistra",
        "city": "Tsakistra",
        "country": "Cyprus",
        "district": "Nicosia District",
        "government-type": "Κοινοτικό Συμβούλιο Τσακίτσρας",
        "government-κοινοτάρχης": "Χριστόδουλος Ορφανίδης",
        "population-total": "79",
        "time-zone": "UTC+2 (EET)",
        "time-zone-summer-(dst)": "UTC+3 (EEST)",
        "lat": "35°1′1″N",
        "long": "32°43′22″E"
    },
    {
        "id": 147,
        "url": "https://en.wikipedia.org/wiki/Tseri",
        "city": "Tseri",
        "country": "Cyprus",
        "district": "Nicosia District",
        "government-mayor": "Alkiviades Constantinou",
        "elevation": "909 ft (277 m)",
        "population-total": "7,035",
        "time-zone": "UTC+2 (EET)",
        "time-zone-summer-(dst)": "UTC+3 (EEST)",
        "website": "www.tseri.org.cy",
        "lat": "35°04′01″N",
        "long": "33°19′00″E"
    },
    {
        "id": 148,
        "url": "https://en.wikipedia.org/wiki/Tymbou",
        "city": "Tymbou",
        "country": "Cyprus",
        "country-district": "Lefkoşa District",
        "country-country-(de-facto)": "Northern Cyprus",
        "population-total": "384",
        "lat": "35°08′05″N",
        "long": "33°31′44″E"
    },
    {
        "id": 149,
        "url": "https://en.wikipedia.org/wiki/Varosha,_Famagusta",
        "city": "Varosha",
        "country": "Cyprus",
        "country-district": "Gazimağusa District",
        "country-country-(de-facto)": "Northern Cyprus",
        "population-total": "226 (Census of Northern Cyprus)",
        "lat": "35°06′39″N",
        "long": "33°57′13″E"
    },
    {
        "id": 150,
        "url": "https://en.wikipedia.org/wiki/Vasilikos_Power_Station",
        "city": "Vasilikos",
        "lat": "34°43′43″N",
        "long": "33°17′24″E"
    },
    {
        "id": 151,
        "url": "https://en.wikipedia.org/wiki/Vavla",
        "city": "Vavla",
        "country": "Cyprus",
        "district": "Larnaca District",
        "population-total": "52",
        "time-zone": "UTC+2 (EET)",
        "time-zone-summer-(dst)": "UTC+3 (EEST)",
        "lat": "34°50′28″N",
        "long": "33°16′4″E"
    },
    {
        "id": 152,
        "url": "https://en.wikipedia.org/wiki/Vouni",
        "city": "Vouni",
        "country": "Cyprus",
        "district": "Limassol District",
        "population-total": "136",
        "time-zone": "UTC+2 (EET)",
        "time-zone-summer-(dst)": "UTC+3 (EEST)",
        "website": "http://www.vouni.org",
        "lat": "34°49′24″N",
        "long": "32°50′1″E"
    },
    {
        "id": 153,
        "url": "https://en.wikipedia.org/wiki/Vretsia",
        "city": "Vretsia",
        "country": "Cyprus",
        "district": "Paphos District",
        "population-total": "0",
        "time-zone": "UTC+2 (EET)",
        "time-zone-summer-(dst)": "UTC+3 (EEST)",
        "postal-code": "6226",
        "lat": "34°53′27″N",
        "long": "32°39′25″E"
    },
    {
        "id": 154,
        "url": "https://en.wikipedia.org/wiki/Frenaros",
        "city": "Vrysoulles",
        "country": "Cyprus",
        "district": "Famagusta District",
        "population-total": "4,298",
        "time-zone": "UTC+2 (EET)",
        "time-zone-summer-(dst)": "UTC+3 (EEST)",
        "website": "phrenaros.org.cy",
        "lat": "35°2′27″N",
        "long": "33°55′9″E"
    },
    {
        "id": 155,
        "url": "https://en.wikipedia.org/wiki/Denizli,_Cyprus",
        "city": "Xeros",
        "country": "Cyprus",
        "country-district": "Lefke District",
        "country-country-(de-facto)": "Northern Cyprus",
        "population-total": "460",
        "time-zone": "UTC+2 (EET)",
        "time-zone-summer-(dst)": "UTC+3 (EEST)",
        "lat": "35°08′50″N",
        "long": "32°51′05″E"
    },
    {
        "id": 156,
        "url": "https://en.wikipedia.org/wiki/Xylofagou",
        "city": "Xylofagou",
        "country": "Cyprus",
        "district": "Larnaca District",
        "population-total": "6,231",
        "time-zone": "UTC+2 (EET)",
        "time-zone-summer-(dst)": "UTC+3 (EEST)",
        "website": "www.xylophagou.com.cy",
        "lat": "34°58′30″N",
        "long": "33°51′6″E"
    },
    {
        "id": 157,
        "url": "https://en.wikipedia.org/wiki/Xylotymbou",
        "city": "Xylotymbou",
        "country": "Cyprus",
        "district": "Larnaca District",
        "government-type": "Community",
        "government-council-president": "Kyriakos G. Papageorgiou",
        "population-total": "3,655",
        "time-zone": "UTC+2 (EET)",
        "time-zone-summer-(dst)": "UTC+3 (EEST)",
        "postal-code": "7510",
        "lat": "35°01′N",
        "long": "33°45′E"
    },
    {
        "id": 158,
        "url": "https://en.wikipedia.org/wiki/Zygi",
        "city": "Zygi",
        "country": "Cyprus",
        "district": "Larnaca District",
        "population-total": "803",
        "time-zone": "UTC+2 (EET)",
        "time-zone-summer-(dst)": "UTC+3 (EEST)",
        "website": "www.zygi.com",
        "lat": "34°44′N",
        "long": "33°20′E"
    }
]